{
    "__comment": "Model generated using MrCrayfish's Model Creator (http://mrcrayfish.com/modelcreator/)",
    "textures": {
        "0": "mbm:blocks/bunkerwall1",
        "1": "mbm:blocks/bunkertrim1top",
        "2": "mbm:blocks/jump_pad",
        "3": "mbm:blocks/jump_pad_particles",
        "particle": "mbm:blocks/bunkerwall1"
    },
    "elements": [
        {
            "name": "Cube",
            "from": [ 1.0, 0.0, 1.0 ], 
            "to": [ 15.0, 2.0, 15.0 ], 
            "faces": {
                "north": { "texture": "#0", "uv": [ 0.0, 0.0, 16.0, 2.0 ] },
                "east": { "texture": "#0", "uv": [ 0.0, 0.0, 16.0, 2.0 ] },
                "south": { "texture": "#0", "uv": [ 0.0, 0.0, 16.0, 2.0 ] },
                "west": { "texture": "#0", "uv": [ 0.0, 0.0, 16.0, 2.0 ] },
                "up": { "texture": "#0", "uv": [ 0.0, 0.0, 14.0, 14.0 ] },
                "down": { "texture": "#1", "uv": [ 0.0, 0.0, 16.0, 16.0 ] }
            }
        },
        {
            "name": "Cube",
            "from": [ 2.0, 2.0, 2.0 ], 
            "to": [ 14.0, 3.0, 14.0 ], 
            "faces": {
                "north": { "texture": "#2", "uv": [ 0.0, 0.0, 16.0, 1.0 ] },
                "east": { "texture": "#2", "uv": [ 0.0, 0.0, 16.0, 1.0 ] },
                "south": { "texture": "#2", "uv": [ 0.0, 0.0, 16.0, 1.0 ] },
                "west": { "texture": "#2", "uv": [ 0.0, 0.0, 16.0, 1.0 ] },
                "up": { "texture": "#2", "uv": [ 0.0, 0.0, 16.0, 16.0 ] },
                "down": { "texture": "#2", "uv": [ 0.0, 0.0, 16.0, 16.0 ] }
            }
        },
        {
            "name": "Cube",
            "from": [ 0.0, 3.0, 8.0 ], 
            "to": [ 16.0, 11.0, 8.0 ], 
            "rotation": { "origin": [ 8.0, 8.0, 8.0 ], "axis": "y", "angle": 45.0 },
            "faces": {
                "north": { "texture": "#3", "uv": [ 0.0, 0.0, 16.0, 16.0 ] },
                "east": { "texture": "#3", "uv": [ 0.0, 0.0, 0.0, 16.0 ] },
                "south": { "texture": "#3", "uv": [ 0.0, 0.0, 16.0, 16.0 ] },
                "west": { "texture": "#3", "uv": [ 0.0, 0.0, 0.0, 8.0 ] },
                "up": { "texture": "#3", "uv": [ 0.0, 0.0, 16.0, 0.0 ] },
                "down": { "texture": "#3", "uv": [ 0.0, 0.0, 16.0, 0.0 ] }
            }
        },
        {
            "name": "Cube",
            "from": [ 0.0, 3.0, 8.0 ], 
            "to": [ 16.0, 11.0, 8.0 ], 
            "rotation": { "origin": [ 8.0, 8.0, 8.0 ], "axis": "y", "angle": -45.0 },
            "faces": {
                "north": { "texture": "#3", "uv": [ 0.0, 0.0, 16.0, 16.0 ] },
                "east": { "texture": "#3", "uv": [ 0.0, 0.0, 0.0, 8.0 ] },
                "south": { "texture": "#3", "uv": [ 0.0, 0.0, 16.0, 16.0 ] },
                "west": { "texture": "#3", "uv": [ 0.0, 0.0, 0.0, 8.0 ] },
                "up": { "texture": "#3", "uv": [ 0.0, 0.0, 16.0, 0.0 ] },
                "down": { "texture": "#3", "uv": [ 0.0, 0.0, 16.0, 0.0 ] }
            }
        }
    ],
    "display":{
        "ground": {
        "translation": [0,4,0],
        "scale": [0.55,0.55,0.55]
        },
        "gui": {
        "rotation":[30,45,0],
        "scale": [0.8,0.8,0.8],
        "translation": [0,2,0]
        },
        "thirdperson_righthand": {
        "rotation": [ 90,0,0],
        "translation": [0,0,3.75],
        "scale": [ 0.5,0.5,0.5]
        },
        "thirdperson_lefthand": {
        "rotation": [ 90,0,0],
        "translation": [0,0,3.75],
        "scale": [ 0.5,0.5,0.5]
        },
        "firstperson_righthand": {
        "rotation": [ 45,0,0],
        "translation": [0,0,0],
        "scale": [ 0.5,0.5,0.5]
        },
        "firstperson_lefthand": {
        "rotation": [ 45,0,0],
        "translation": [0,0,0],
        "scale": [ 0.5,0.5,0.5]
        }
    }
}